django_render/__init__.py
django_render/apps.py
django_render/decorators.py
django_render/middleware.py
django_render/response.py
django_render/telepath.py
django_render/views.py
django_render/adapters/__init__.py
django_render/adapters/forms.py
django_render/adapters/registry.py
django_render/static/django_render/fonts/.gitignore
django_render/static/django_render/images/.gitignore
django_render/static/django_render/js/.gitignore
django_render/templates/django_render/bootstrap.html
django_render/test/__init__.py
django_render/test/apps.py
django_render/test/settings.py
django_render/test/urls.py
django_render/test/tests/__init__.py
django_render/ui/__init__.py
django_render/ui/forms.py
djangorender/__init__.py
djangorender/apps.py
djangorender/decorators.py
djangorender/response.py
djangorender/telepath.py
djangorender/views.py
djangorender/static/djangorender/fonts/.gitignore
djangorender/static/djangorender/images/.gitignore
djangorender/static/djangorender/js/.gitignore
djangorender/templates/djangorender/bootstrap.html
djangorender/test/__init__.py
djangorender/test/apps.py
djangorender/test/settings.py
djangorender/test/urls.py
djangorender/test/tests/__init__.py
djangorender/ui/__init__.py
djangorender/ui/forms.py
django_spa_kit-0.1.dist-info/METADATA
django_spa_kit-0.1.dist-info/WHEEL
django_spa_kit-0.1.dist-info/top_level.txt
django_spa_kit-0.1.dist-info/RECORD
